LICENSE.md
setup.py
electrasmart/__init__.py
electrasmart/cli.py
electrasmart/client.py
electrasmart.egg-info/PKG-INFO
electrasmart.egg-info/SOURCES.txt
electrasmart.egg-info/dependency_links.txt
electrasmart.egg-info/entry_points.txt
electrasmart.egg-info/requires.txt
electrasmart.egg-info/top_level.txt